adafruit_shtc3.py
adafruit_circuitpython_shtc3-1.1.20.dist-info/licenses/LICENSE
adafruit_circuitpython_shtc3-1.1.20.dist-info/METADATA
adafruit_circuitpython_shtc3-1.1.20.dist-info/WHEEL
adafruit_circuitpython_shtc3-1.1.20.dist-info/top_level.txt
adafruit_circuitpython_shtc3-1.1.20.dist-info/RECORD
